{
  "metadata": {
    "source": "ACTAWP",
    "team_key": "juvenil",
    "team_id": "15621223",
    "team_name": "CN Terrassa Juvenil",
    "coach": "Jordi Busquets",
    "downloaded_at": "2026-02-04T14:24:40.855268",
    "parser_version": "6.3_calendar_dates"
  },
  "players": [
    {
      "Nombre": "ADAY ACUÑA PRADAS",
      "PJ": 3,
      "GT": 0,
      "G": 0,
      "GP": 0,
      "G5P": 0,
      "TA": 0,
      "TR": 0,
      "EX": 5,
      "ED": 0,
      "EB": 0,
      "EN": 0,
      "EP": 0,
      "P": 2,
      "PF": 0,
      "O": 0,
      "TM": 0,
      "JL": 0,
      "MVP": 0
    },
    {
      "Nombre": "ALAN GONZALEZ ARRIBAS",
      "PJ": 0,
      "GT": 0,
      "G": 0,
      "GP": 0,
      "G5P": 0,
      "TA": 0,
      "TR": 0,
      "EX": 0,
      "ED": 0,
      "EB": 0,
      "EN": 0,
      "EP": 0,
      "P": 0,
      "PF": 0,
      "O": 0,
      "TM": 0,
      "JL": 0,
      "MVP": 0
    },
    {
      "Nombre": "ARNAU MERCADE SEGURA",
      "PJ": 8,
      "GT": 14,
      "G": 13,
      "GP": 1,
      "G5P": 0,
      "TA": 0,
      "TR": 0,
      "EX": 12,
      "ED": 0,
      "EB": 0,
      "EN": 0,
      "EP": 0,
      "P": 2,
      "PF": 1,
      "O": 0,
      "TM": 0,
      "JL": 0,
      "MVP": 0
    },
    {
      "Nombre": "BIEL GARCIA ARJONA",
      "PJ": 7,
      "GT": 4,
      "G": 4,
      "GP": 0,
      "G5P": 0,
      "TA": 0,
      "TR": 0,
      "EX": 5,
      "ED": 0,
      "EB": 0,
      "EN": 0,
      "EP": 0,
      "P": 0,
      "PF": 0,
      "O": 0,
      "TM": 0,
      "JL": 0,
      "MVP": 0
    },
    {
      "Nombre": "ERIC MORA FERNANDEZ",
      "PJ": 7,
      "GT": 0,
      "G": 0,
      "GP": 0,
      "G5P": 0,
      "TA": 0,
      "TR": 0,
      "EX": 0,
      "ED": 0,
      "EB": 0,
      "EN": 0,
      "EP": 0,
      "P": 1,
      "PF": 0,
      "O": 0,
      "TM": 0,
      "JL": 0,
      "MVP": 0
    },
    {
      "Nombre": "ERIC VILLAREAL MURIEL",
      "PJ": 0,
      "GT": 0,
      "G": 0,
      "GP": 0,
      "G5P": 0,
      "TA": 0,
      "TR": 0,
      "EX": 0,
      "ED": 0,
      "EB": 0,
      "EN": 0,
      "EP": 0,
      "P": 0,
      "PF": 0,
      "O": 0,
      "TM": 0,
      "JL": 0,
      "MVP": 0
    },
    {
      "Nombre": "HECTOR DIOS ESTEBAN",
      "PJ": 6,
      "GT": 3,
      "G": 3,
      "GP": 0,
      "G5P": 0,
      "TA": 0,
      "TR": 0,
      "EX": 7,
      "ED": 0,
      "EB": 0,
      "EN": 0,
      "EP": 0,
      "P": 1,
      "PF": 0,
      "O": 0,
      "TM": 0,
      "JL": 0,
      "MVP": 0
    },
    {
      "Nombre": "IAN BARTOLOME COLLADO",
      "PJ": 8,
      "GT": 7,
      "G": 7,
      "GP": 0,
      "G5P": 0,
      "TA": 0,
      "TR": 0,
      "EX": 7,
      "ED": 0,
      "EB": 0,
      "EN": 0,
      "EP": 0,
      "P": 0,
      "PF": 0,
      "O": 0,
      "TM": 0,
      "JL": 0,
      "MVP": 0
    },
    {
      "Nombre": "JORDI TARRADAS VARGAS",
      "PJ": 8,
      "GT": 10,
      "G": 10,
      "GP": 0,
      "G5P": 0,
      "TA": 0,
      "TR": 0,
      "EX": 14,
      "ED": 0,
      "EB": 0,
      "EN": 0,
      "EP": 0,
      "P": 1,
      "PF": 0,
      "O": 0,
      "TM": 0,
      "JL": 0,
      "MVP": 0
    },
    {
      "Nombre": "LLATZER PEREZ BARADAD",
      "PJ": 5,
      "GT": 5,
      "G": 5,
      "GP": 0,
      "G5P": 0,
      "TA": 0,
      "TR": 0,
      "EX": 2,
      "ED": 0,
      "EB": 0,
      "EN": 0,
      "EP": 0,
      "P": 0,
      "PF": 0,
      "O": 0,
      "TM": 0,
      "JL": 0,
      "MVP": 0
    },
    {
      "Nombre": "MARC CAMPAÑA SALVADOR",
      "PJ": 6,
      "GT": 3,
      "G": 3,
      "GP": 0,
      "G5P": 0,
      "TA": 0,
      "TR": 0,
      "EX": 3,
      "ED": 0,
      "EB": 0,
      "EN": 0,
      "EP": 0,
      "P": 2,
      "PF": 0,
      "O": 0,
      "TM": 0,
      "JL": 0,
      "MVP": 0
    },
    {
      "Nombre": "MARC MORENO FOLCH",
      "PJ": 8,
      "GT": 4,
      "G": 2,
      "GP": 2,
      "G5P": 0,
      "TA": 0,
      "TR": 0,
      "EX": 9,
      "ED": 0,
      "EB": 0,
      "EN": 0,
      "EP": 0,
      "P": 1,
      "PF": 0,
      "O": 0,
      "TM": 0,
      "JL": 0,
      "MVP": 0
    },
    {
      "Nombre": "MARTI ARIMON HUMET",
      "PJ": 8,
      "GT": 29,
      "G": 24,
      "GP": 5,
      "G5P": 0,
      "TA": 0,
      "TR": 0,
      "EX": 8,
      "ED": 0,
      "EB": 0,
      "EN": 0,
      "EP": 0,
      "P": 0,
      "PF": 4,
      "O": 0,
      "TM": 0,
      "JL": 0,
      "MVP": 0
    },
    {
      "Nombre": "MAX VALLS FORNIELES",
      "PJ": 9,
      "GT": 0,
      "G": 0,
      "GP": 0,
      "G5P": 0,
      "TA": 0,
      "TR": 0,
      "EX": 3,
      "ED": 0,
      "EB": 0,
      "EN": 0,
      "EP": 0,
      "P": 0,
      "PF": 0,
      "O": 0,
      "TM": 0,
      "JL": 0,
      "MVP": 0
    },
    {
      "Nombre": "ORIOL SANCHEZ CARRILLO",
      "PJ": 9,
      "GT": 38,
      "G": 37,
      "GP": 1,
      "G5P": 0,
      "TA": 0,
      "TR": 0,
      "EX": 6,
      "ED": 0,
      "EB": 0,
      "EN": 0,
      "EP": 0,
      "P": 1,
      "PF": 2,
      "O": 0,
      "TM": 0,
      "JL": 0,
      "MVP": 0
    },
    {
      "Nombre": "POL RICO SANAHUJA",
      "PJ": 8,
      "GT": 6,
      "G": 5,
      "GP": 1,
      "G5P": 0,
      "TA": 0,
      "TR": 0,
      "EX": 8,
      "ED": 0,
      "EB": 0,
      "EN": 0,
      "EP": 0,
      "P": 0,
      "PF": 0,
      "O": 0,
      "TM": 0,
      "JL": 0,
      "MVP": 0
    },
    {
      "Nombre": "ROGER FARRE AMADOR",
      "PJ": 6,
      "GT": 7,
      "G": 6,
      "GP": 1,
      "G5P": 0,
      "TA": 0,
      "TR": 0,
      "EX": 5,
      "ED": 0,
      "EB": 0,
      "EN": 0,
      "EP": 0,
      "P": 1,
      "PF": 0,
      "O": 0,
      "TM": 0,
      "JL": 0,
      "MVP": 0
    },
    {
      "Nombre": "ROGER ROVIRA MARTINEZ",
      "PJ": 3,
      "GT": 1,
      "G": 1,
      "GP": 0,
      "G5P": 0,
      "TA": 0,
      "TR": 0,
      "EX": 3,
      "ED": 0,
      "EB": 0,
      "EN": 0,
      "EP": 0,
      "P": 1,
      "PF": 0,
      "O": 0,
      "TM": 0,
      "JL": 0,
      "MVP": 0
    },
    {
      "Nombre": "SAMUEL DIAZ MARROQUIN",
      "PJ": 9,
      "GT": 15,
      "G": 14,
      "GP": 1,
      "G5P": 0,
      "TA": 0,
      "TR": 0,
      "EX": 4,
      "ED": 0,
      "EB": 0,
      "EN": 0,
      "EP": 0,
      "P": 3,
      "PF": 0,
      "O": 0,
      "TM": 0,
      "JL": 0,
      "MVP": 0
    },
    {
      "Nombre": "YABSIRA CASADO FUENTES",
      "PJ": 0,
      "GT": 0,
      "G": 0,
      "GP": 0,
      "G5P": 0,
      "TA": 0,
      "TR": 0,
      "EX": 0,
      "ED": 0,
      "EB": 0,
      "EN": 0,
      "EP": 0,
      "P": 0,
      "PF": 0,
      "O": 0,
      "TM": 0,
      "JL": 0,
      "MVP": 0
    }
  ],
  "team_stats": {
    "Puntos": 21,
    "A favor": 146,
    "En contra": 91,
    "Partidos jugados": 9,
    "Partidos ganados": 7,
    "Partidos empatados": 0,
    "Partidos perdidos": 2,
    "Goles de penalti": 12,
    "Expulsiones por 20 segundos": 101,
    "Tarjetas amarillas": 1,
    "Goles": 134,
    "Faltas por penalti": 16,
    "Penaltis fallados": 7,
    "Tiempos muertos": 12
  },
  "upcoming_matches": [
    {
      "team1": "C.N. TERRASSA",
      "team2": "C.N. SABADELL",
      "team1_logo": "https://cdn.leverade.com/thumbnails/rfen_f74fa6fe.30x30.jpg",
      "team2_logo": "https://cdn.leverade.com/thumbnails/AaJFwTq1SdZo.30x30.jpg",
      "date_time": "Dom, 08/02/2026 12:55 163 - Terrassa C.N.",
      "jornada": 1,
      "url": "https://actawp.natacio.cat/es/tournament/1317471/match/144027314/results",
      "date": "08/02/2026",
      "time": "12:55"
    },
    {
      "team1": "C.N. MONTJUIC A",
      "team2": "C.N. TERRASSA",
      "team1_logo": "https://cdn.leverade.com/thumbnails/AaLZ2cLfo4fC.30x30.jpg",
      "team2_logo": "https://cdn.leverade.com/thumbnails/rfen_f74fa6fe.30x30.jpg",
      "date_time": "Dom, 15/02/2026 10:15 163 - Terrassa C.N.",
      "jornada": 2,
      "url": "https://actawp.natacio.cat/es/tournament/1317471/match/144027318/results",
      "date": "15/02/2026",
      "time": "10:15"
    },
    {
      "team1": "C.E. MEDITERRANI",
      "team2": "C.N. TERRASSA",
      "team1_logo": "https://cdn.leverade.com/thumbnails/AasntmnZMsxi.30x30.jpg",
      "team2_logo": "https://cdn.leverade.com/thumbnails/rfen_f74fa6fe.30x30.jpg",
      "date_time": "Dom, 22/02/2026 09:30 258 - Mediterrani CE, Josep Vallès - 50m",
      "jornada": 3,
      "url": "https://actawp.natacio.cat/es/tournament/1317471/match/144027323/results",
      "date": "22/02/2026",
      "time": "09:30"
    },
    {
      "team1": "C.N. TERRASSA",
      "team2": "C.N. BARCELONA",
      "team1_logo": "https://cdn.leverade.com/thumbnails/rfen_f74fa6fe.30x30.jpg",
      "team2_logo": "https://cdn.leverade.com/thumbnails/AaT38Tf1E4Fg.30x30.jpg",
      "date_time": "Dom, 01/03/2026 09:00 163 - Terrassa C.N.",
      "jornada": 4,
      "url": "https://actawp.natacio.cat/es/tournament/1317471/match/144027305/results",
      "date": "01/03/2026",
      "time": "09:00"
    },
    {
      "team1": "C.N. TERRASSA",
      "team2": "C.N. ATL BARCELONETA",
      "team1_logo": "https://cdn.leverade.com/thumbnails/rfen_f74fa6fe.30x30.jpg",
      "team2_logo": "https://cdn.leverade.com/thumbnails/AaS9iMCevN9M.30x30.jpg",
      "date_time": "Dom, 08/03/2026 09:00 163 - Terrassa C.N.",
      "jornada": 5,
      "url": "https://actawp.natacio.cat/es/tournament/1317471/match/144027324/results",
      "date": "08/03/2026",
      "time": "09:00"
    },
    {
      "team1": "C.N. TERRASSA",
      "team2": "U.E. D'HORTA",
      "team1_logo": "https://cdn.leverade.com/thumbnails/rfen_f74fa6fe.30x30.jpg",
      "team2_logo": "https://cdn.leverade.com/thumbnails/AaEBEa7OVvwB.30x30.jpg",
      "date_time": "Dom, 15/03/2026 12:55 163 - Terrassa C.N.",
      "jornada": 6,
      "url": "https://actawp.natacio.cat/es/tournament/1317471/match/144027328/results",
      "date": "15/03/2026",
      "time": "12:55"
    },
    {
      "team1": "C.N. SANT ANDREU",
      "team2": "C.N. TERRASSA",
      "team1_logo": "https://cdn.leverade.com/thumbnails/AaTcV9fsgKzp.30x30.jpg",
      "team2_logo": "https://cdn.leverade.com/thumbnails/rfen_f74fa6fe.30x30.jpg",
      "date_time": "Vie, 20/03/2026 21:15 164 - St Andreu, CN (25 M.)",
      "jornada": 7,
      "url": "https://actawp.natacio.cat/es/tournament/1317471/match/144027309/results",
      "date": "20/03/2026",
      "time": "21:15"
    },
    {
      "team1": "C.N. BARCELONA",
      "team2": "C.N. TERRASSA",
      "team1_logo": "https://cdn.leverade.com/thumbnails/AaT38Tf1E4Fg.30x30.jpg",
      "team2_logo": "https://cdn.leverade.com/thumbnails/rfen_f74fa6fe.30x30.jpg",
      "date_time": "Dom, 22/03/2026 09:30 160 - Barcelona, CN - Nova Escollera - 50m",
      "jornada": 8,
      "url": "https://actawp.natacio.cat/es/tournament/1317471/match/144027333/results",
      "date": "22/03/2026",
      "time": "09:30"
    },
    {
      "team1": "C.N. SABADELL",
      "team2": "C.N. TERRASSA",
      "team1_logo": "https://cdn.leverade.com/thumbnails/AaJFwTq1SdZo.30x30.jpg",
      "team2_logo": "https://cdn.leverade.com/thumbnails/rfen_f74fa6fe.30x30.jpg",
      "date_time": "Dom, 19/04/2026 12:45 264 - Sabadell, CN - Can Llong - 33m",
      "jornada": 9,
      "url": "https://actawp.natacio.cat/es/tournament/1317471/match/144027342/results",
      "date": "19/04/2026",
      "time": "12:45"
    },
    {
      "team1": "C.N. TERRASSA",
      "team2": "C.N. SANT ANDREU",
      "team1_logo": "https://cdn.leverade.com/thumbnails/rfen_f74fa6fe.30x30.jpg",
      "team2_logo": "https://cdn.leverade.com/thumbnails/AaTcV9fsgKzp.30x30.jpg",
      "date_time": "Mié, 22/04/2026 21:00 163 - Terrassa C.N.",
      "jornada": 10,
      "url": "https://actawp.natacio.cat/es/tournament/1317471/match/144027337/results",
      "date": "22/04/2026",
      "time": "21:00"
    },
    {
      "team1": "C.N. TERRASSA",
      "team2": "C.N. MONTJUIC A",
      "team1_logo": "https://cdn.leverade.com/thumbnails/rfen_f74fa6fe.30x30.jpg",
      "team2_logo": "https://cdn.leverade.com/thumbnails/AaLZ2cLfo4fC.30x30.jpg",
      "date_time": "Dom, 26/04/2026 12:55 163 - Terrassa C.N.",
      "jornada": 11,
      "url": "https://actawp.natacio.cat/es/tournament/1317471/match/144027346/results",
      "date": "26/04/2026",
      "time": "12:55"
    },
    {
      "team1": "C.N. TERRASSA",
      "team2": "C.E. MEDITERRANI",
      "team1_logo": "https://cdn.leverade.com/thumbnails/rfen_f74fa6fe.30x30.jpg",
      "team2_logo": "https://cdn.leverade.com/thumbnails/AasntmnZMsxi.30x30.jpg",
      "date_time": "Dom, 10/05/2026 12:55 163 - Terrassa C.N.",
      "jornada": 12,
      "url": "https://actawp.natacio.cat/es/tournament/1317471/match/144027351/results",
      "date": "10/05/2026",
      "time": "12:55"
    },
    {
      "team1": "C.N. ATL BARCELONETA",
      "team2": "C.N. TERRASSA",
      "team1_logo": "https://cdn.leverade.com/thumbnails/AaS9iMCevN9M.30x30.jpg",
      "team2_logo": "https://cdn.leverade.com/thumbnails/rfen_f74fa6fe.30x30.jpg",
      "date_time": "Dom, 17/05/2026 09:15 166 - Atlètic Barceloneta, CN - 33m coberta",
      "jornada": 13,
      "url": "https://actawp.natacio.cat/es/tournament/1317471/match/144027352/results",
      "date": "17/05/2026",
      "time": "09:15"
    }
  ],
  "last_results": [
    {
      "team1": "U.E. D'HORTA",
      "team2": "C.N. TERRASSA",
      "team1_logo": "https://cdn.leverade.com/thumbnails/AaEBEa7OVvwB.30x30.jpg",
      "team2_logo": "https://cdn.leverade.com/thumbnails/rfen_f74fa6fe.30x30.jpg",
      "score": "16-13",
      "date": "",
      "jornada": 1,
      "url": "https://actawp.natacio.cat/es/tournament/1317471/match/144027300/results"
    },
    {
      "team1": "C.N. TERRASSA",
      "team2": "C.N. RUBÍ",
      "team1_logo": "https://cdn.leverade.com/thumbnails/rfen_f74fa6fe.30x30.jpg",
      "team2_logo": "https://cdn.leverade.com/thumbnails/Aa0ntlmDPJHS.30x30.jpg",
      "score": "13-4",
      "date": "",
      "jornada": 2,
      "url": "https://actawp.natacio.cat/es/tournament/1317471/match/143574247/results"
    },
    {
      "team1": "C.E. MEDITERRANI",
      "team2": "C.N. TERRASSA",
      "team1_logo": "https://cdn.leverade.com/thumbnails/AasntmnZMsxi.30x30.jpg",
      "team2_logo": "https://cdn.leverade.com/thumbnails/rfen_f74fa6fe.30x30.jpg",
      "score": "11-12",
      "date": "",
      "jornada": 3,
      "url": "https://actawp.natacio.cat/es/tournament/1317471/match/143574245/results"
    },
    {
      "team1": "C.N. TERRASSA",
      "team2": "C.N. MONTJUIC B",
      "team1_logo": "https://cdn.leverade.com/thumbnails/rfen_f74fa6fe.30x30.jpg",
      "team2_logo": "https://cdn.leverade.com/thumbnails/AaLZ2cLfo4fC.30x30.jpg",
      "score": "25-10",
      "date": "",
      "jornada": 4,
      "url": "https://actawp.natacio.cat/es/tournament/1317471/match/143574238/results"
    },
    {
      "team1": "C.N. RUBÍ",
      "team2": "C.N. TERRASSA",
      "team1_logo": "https://cdn.leverade.com/thumbnails/Aa0ntlmDPJHS.30x30.jpg",
      "team2_logo": "https://cdn.leverade.com/thumbnails/rfen_f74fa6fe.30x30.jpg",
      "score": "8-12",
      "date": "",
      "jornada": 5,
      "url": "https://actawp.natacio.cat/es/tournament/1317471/match/143574241/results"
    },
    {
      "team1": "C.N. TERRASSA",
      "team2": "C.E. MEDITERRANI",
      "team1_logo": "https://cdn.leverade.com/thumbnails/rfen_f74fa6fe.30x30.jpg",
      "team2_logo": "https://cdn.leverade.com/thumbnails/AasntmnZMsxi.30x30.jpg",
      "score": "7-15",
      "date": "",
      "jornada": 6,
      "url": "https://actawp.natacio.cat/es/tournament/1317471/match/143574239/results"
    },
    {
      "team1": "C.N. MONTJUIC B",
      "team2": "C.N. TERRASSA",
      "team1_logo": "https://cdn.leverade.com/thumbnails/AaLZ2cLfo4fC.30x30.jpg",
      "team2_logo": "https://cdn.leverade.com/thumbnails/rfen_f74fa6fe.30x30.jpg",
      "score": "10-21",
      "date": "",
      "jornada": 7,
      "url": "https://actawp.natacio.cat/es/tournament/1317471/match/143574244/results"
    },
    {
      "team1": "C.N. TERRASSA",
      "team2": "C.N. MOLINS DE REI",
      "team1_logo": "https://cdn.leverade.com/thumbnails/rfen_f74fa6fe.30x30.jpg",
      "team2_logo": "https://cdn.leverade.com/thumbnails/rfen_f4fc6ccd.30x30.jpg",
      "score": "23-7",
      "date": "",
      "jornada": 8,
      "url": "https://actawp.natacio.cat/es/tournament/1317471/match/143253265/results"
    },
    {
      "team1": "C.N. MONTJUIC A",
      "team2": "C.N. TERRASSA",
      "team1_logo": "https://cdn.leverade.com/thumbnails/AaLZ2cLfo4fC.30x30.jpg",
      "team2_logo": "https://cdn.leverade.com/thumbnails/rfen_f74fa6fe.30x30.jpg",
      "score": "10-20",
      "date": "",
      "jornada": 9,
      "url": "https://actawp.natacio.cat/es/tournament/1317471/match/143253266/results"
    }
  ],
  "ranking": [
    {
      "posicio": "1",
      "equip": "C.N. SABADELL",
      "team_id": "15616560",
      "logo": "https://cdn.leverade.com/thumbnails/AaJFwTq1SdZo.30x30.jpg",
      "punts": 9,
      "partits": 3,
      "guanyats": 3,
      "empatats": 0,
      "perduts": 0,
      "gols_favor": 51,
      "gols_contra": 27,
      "diferencia": 24
    },
    {
      "posicio": "2",
      "equip": "C.N. ATL BARCELONETA",
      "team_id": "15617346",
      "logo": "https://cdn.leverade.com/thumbnails/AaS9iMCevN9M.30x30.jpg",
      "punts": 6,
      "partits": 2,
      "guanyats": 2,
      "empatats": 0,
      "perduts": 0,
      "gols_favor": 28,
      "gols_contra": 16,
      "diferencia": 12
    },
    {
      "posicio": "3",
      "equip": "U.E. D'HORTA",
      "team_id": "15609765",
      "logo": "https://cdn.leverade.com/thumbnails/AaEBEa7OVvwB.30x30.jpg",
      "punts": 6,
      "partits": 3,
      "guanyats": 2,
      "empatats": 0,
      "perduts": 1,
      "gols_favor": 37,
      "gols_contra": 38,
      "diferencia": -1
    },
    {
      "posicio": "4",
      "equip": "C.N. BARCELONA",
      "team_id": "15612054",
      "logo": "https://cdn.leverade.com/thumbnails/AaT38Tf1E4Fg.30x30.jpg",
      "punts": 3,
      "partits": 1,
      "guanyats": 1,
      "empatats": 0,
      "perduts": 0,
      "gols_favor": 23,
      "gols_contra": 3,
      "diferencia": 20
    },
    {
      "posicio": "5",
      "equip": "C.N. SANT ANDREU",
      "team_id": "15617612",
      "logo": "https://cdn.leverade.com/thumbnails/AaTcV9fsgKzp.30x30.jpg",
      "punts": 3,
      "partits": 2,
      "guanyats": 1,
      "empatats": 0,
      "perduts": 1,
      "gols_favor": 23,
      "gols_contra": 26,
      "diferencia": -3
    },
    {
      "posicio": "6",
      "equip": "C.N. TERRASSA",
      "team_id": "15621223",
      "logo": "https://cdn.leverade.com/thumbnails/rfen_f74fa6fe.30x30.jpg",
      "punts": 0,
      "partits": 1,
      "guanyats": 0,
      "empatats": 0,
      "perduts": 1,
      "gols_favor": 13,
      "gols_contra": 16,
      "diferencia": -3
    },
    {
      "posicio": "7",
      "equip": "C.E. MEDITERRANI",
      "team_id": "15609737",
      "logo": "https://cdn.leverade.com/thumbnails/AasntmnZMsxi.30x30.jpg",
      "punts": 0,
      "partits": 3,
      "guanyats": 0,
      "empatats": 0,
      "perduts": 3,
      "gols_favor": 26,
      "gols_contra": 35,
      "diferencia": -9
    },
    {
      "posicio": "8",
      "equip": "C.N. MONTJUIC A",
      "team_id": "15617365",
      "logo": "https://cdn.leverade.com/thumbnails/AaLZ2cLfo4fC.30x30.jpg",
      "punts": 0,
      "partits": 3,
      "guanyats": 0,
      "empatats": 0,
      "perduts": 3,
      "gols_favor": 21,
      "gols_contra": 61,
      "diferencia": -40
    }
  ],
  "rivals_form": {
    "C.N. SABADELL": {
      "team_id": "15616560",
      "last_results": [
        {
          "team1": "C.N. SANT ANDREU",
          "team2": "C.N. SABADELL",
          "team1_logo": "https://cdn.leverade.com/thumbnails/AaTcV9fsgKzp.30x30.jpg",
          "team2_logo": "https://cdn.leverade.com/thumbnails/AaJFwTq1SdZo.30x30.jpg",
          "score": "8-14",
          "date": "",
          "jornada": 1,
          "url": "https://actawp.natacio.cat/es/tournament/1317471/match/144027302/results"
        },
        {
          "team1": "C.N. SABADELL",
          "team2": "C.N. MONTJUIC A",
          "team1_logo": "https://cdn.leverade.com/thumbnails/AaJFwTq1SdZo.30x30.jpg",
          "team2_logo": "https://cdn.leverade.com/thumbnails/AaLZ2cLfo4fC.30x30.jpg",
          "score": "23-6",
          "date": "",
          "jornada": 2,
          "url": "https://actawp.natacio.cat/es/tournament/1317471/match/144027310/results"
        },
        {
          "team1": "C.E. MEDITERRANI",
          "team2": "C.N. SABADELL",
          "team1_logo": "https://cdn.leverade.com/thumbnails/AasntmnZMsxi.30x30.jpg",
          "team2_logo": "https://cdn.leverade.com/thumbnails/AaJFwTq1SdZo.30x30.jpg",
          "score": "13-14",
          "date": "",
          "jornada": 3,
          "url": "https://actawp.natacio.cat/es/tournament/1317471/match/144027307/results"
        },
        {
          "team1": "C.N. SABADELL",
          "team2": "C.N. SANT FELIU",
          "team1_logo": "https://cdn.leverade.com/thumbnails/AaJFwTq1SdZo.30x30.jpg",
          "team2_logo": "https://cdn.leverade.com/thumbnails/AaHuNvh2GCD0.30x30.jpg",
          "score": "23-10",
          "date": "",
          "jornada": 4,
          "url": "https://actawp.natacio.cat/es/tournament/1317471/match/143574235/results"
        },
        {
          "team1": "C.N. SABADELL",
          "team2": "C.N. MONTJUIC A",
          "team1_logo": "https://cdn.leverade.com/thumbnails/AaJFwTq1SdZo.30x30.jpg",
          "team2_logo": "https://cdn.leverade.com/thumbnails/AaLZ2cLfo4fC.30x30.jpg",
          "score": "13-5",
          "date": "",
          "jornada": 5,
          "url": "https://actawp.natacio.cat/es/tournament/1317471/match/143574227/results"
        }
      ],
      "form": [
        "W",
        "W",
        "W",
        "W",
        "W"
      ],
      "form_string": "WWWWW",
      "top_scorers": [
        {
          "name": "DAAN KNIP SANCHEZ",
          "goals": 26,
          "games": 9,
          "exclusions": 8,
          "penalty_goals": 4,
          "avg_goals": 2.89
        },
        {
          "name": "GUILLEM NAVARRO PICAZO",
          "goals": 25,
          "games": 9,
          "exclusions": 7,
          "penalty_goals": 4,
          "avg_goals": 2.78
        },
        {
          "name": "EDGAR VILCHEZ RUIZ",
          "goals": 24,
          "games": 9,
          "exclusions": 4,
          "penalty_goals": 0,
          "avg_goals": 2.67
        },
        {
          "name": "GENIS BATISTA ALFONSO",
          "goals": 22,
          "games": 8,
          "exclusions": 6,
          "penalty_goals": 6,
          "avg_goals": 2.75
        },
        {
          "name": "NIKITA RUDOI BOBULICI",
          "goals": 16,
          "games": 9,
          "exclusions": 3,
          "penalty_goals": 0,
          "avg_goals": 1.78
        }
      ],
      "stats": {
        "total_gf": 87,
        "total_gc": 42,
        "avg_gf": 17.4,
        "avg_gc": 8.4,
        "matches_played": 5,
        "wins": 5,
        "draws": 0,
        "losses": 0,
        "trend": "hot",
        "total_exclusions": 28
      }
    },
    "C.N. ATL BARCELONETA": {
      "team_id": "15617346",
      "last_results": [
        {
          "team1": "C.N. ATL BARCELONETA",
          "team2": "U.E. D'HORTA",
          "team1_logo": "https://cdn.leverade.com/thumbnails/AaS9iMCevN9M.30x30.jpg",
          "team2_logo": "https://cdn.leverade.com/thumbnails/AaEBEa7OVvwB.30x30.jpg",
          "score": "17-11",
          "date": "",
          "jornada": 1,
          "url": "https://actawp.natacio.cat/es/tournament/1317471/match/144027304/results"
        },
        {
          "team1": "C.N. ATL BARCELONETA",
          "team2": "C.E. MEDITERRANI",
          "team1_logo": "https://cdn.leverade.com/thumbnails/AaS9iMCevN9M.30x30.jpg",
          "team2_logo": "https://cdn.leverade.com/thumbnails/AasntmnZMsxi.30x30.jpg",
          "score": "11-5",
          "date": "",
          "jornada": 2,
          "url": "https://actawp.natacio.cat/es/tournament/1317471/match/144027303/results"
        },
        {
          "team1": "C.N. ATL BARCELONETA",
          "team2": "C.N. MOLINS DE REI",
          "team1_logo": "https://cdn.leverade.com/thumbnails/AaS9iMCevN9M.30x30.jpg",
          "team2_logo": "https://cdn.leverade.com/thumbnails/rfen_f4fc6ccd.30x30.jpg",
          "score": "21-3",
          "date": "",
          "jornada": 3,
          "url": "https://actawp.natacio.cat/es/tournament/1317471/match/143574182/results"
        },
        {
          "team1": "U.E. D'HORTA",
          "team2": "C.N. ATL BARCELONETA",
          "team1_logo": "https://cdn.leverade.com/thumbnails/AaEBEa7OVvwB.30x30.jpg",
          "team2_logo": "https://cdn.leverade.com/thumbnails/AaS9iMCevN9M.30x30.jpg",
          "score": "5-22",
          "date": "",
          "jornada": 4,
          "url": "https://actawp.natacio.cat/es/tournament/1317471/match/143574180/results"
        },
        {
          "team1": "C.N. PREMIÀ",
          "team2": "C.N. ATL BARCELONETA",
          "team1_logo": "https://cdn.leverade.com/thumbnails/AatzEPbjSvDt.30x30.jpg",
          "team2_logo": "https://cdn.leverade.com/thumbnails/AaS9iMCevN9M.30x30.jpg",
          "score": "4-28",
          "date": "",
          "jornada": 5,
          "url": "https://actawp.natacio.cat/es/tournament/1317471/match/143574179/results"
        }
      ],
      "form": [
        "W",
        "W",
        "W",
        "W",
        "W"
      ],
      "form_string": "WWWWW",
      "top_scorers": [
        {
          "name": "DANIEL MERIDA OROZCO",
          "goals": 30,
          "games": 8,
          "exclusions": 7,
          "penalty_goals": 2,
          "avg_goals": 3.75
        },
        {
          "name": "ENZO FERNANDEZ PERRIER",
          "goals": 26,
          "games": 7,
          "exclusions": 5,
          "penalty_goals": 2,
          "avg_goals": 3.71
        },
        {
          "name": "DANYLO BENYAKH",
          "goals": 22,
          "games": 8,
          "exclusions": 2,
          "penalty_goals": 0,
          "avg_goals": 2.75
        },
        {
          "name": "CESC AGUIRRE RUBIO",
          "goals": 20,
          "games": 10,
          "exclusions": 2,
          "penalty_goals": 5,
          "avg_goals": 2.0
        },
        {
          "name": "MARCOS ELCHE HERNANDEZ",
          "goals": 20,
          "games": 7,
          "exclusions": 6,
          "penalty_goals": 4,
          "avg_goals": 2.86
        }
      ],
      "stats": {
        "total_gf": 99,
        "total_gc": 28,
        "avg_gf": 19.8,
        "avg_gc": 5.6,
        "matches_played": 5,
        "wins": 5,
        "draws": 0,
        "losses": 0,
        "trend": "hot",
        "total_exclusions": 22
      }
    },
    "U.E. D'HORTA": {
      "team_id": "15609765",
      "last_results": [
        {
          "team1": "U.E. D'HORTA",
          "team2": "C.E. MEDITERRANI",
          "team1_logo": "https://cdn.leverade.com/thumbnails/AaEBEa7OVvwB.30x30.jpg",
          "team2_logo": "https://cdn.leverade.com/thumbnails/AasntmnZMsxi.30x30.jpg",
          "score": "10-8",
          "date": "",
          "jornada": 1,
          "url": "https://actawp.natacio.cat/es/tournament/1317471/match/144027311/results"
        },
        {
          "team1": "C.N. ATL BARCELONETA",
          "team2": "U.E. D'HORTA",
          "team1_logo": "https://cdn.leverade.com/thumbnails/AaS9iMCevN9M.30x30.jpg",
          "team2_logo": "https://cdn.leverade.com/thumbnails/AaEBEa7OVvwB.30x30.jpg",
          "score": "17-11",
          "date": "",
          "jornada": 2,
          "url": "https://actawp.natacio.cat/es/tournament/1317471/match/144027304/results"
        },
        {
          "team1": "U.E. D'HORTA",
          "team2": "C.N. TERRASSA",
          "team1_logo": "https://cdn.leverade.com/thumbnails/AaEBEa7OVvwB.30x30.jpg",
          "team2_logo": "https://cdn.leverade.com/thumbnails/rfen_f74fa6fe.30x30.jpg",
          "score": "16-13",
          "date": "",
          "jornada": 3,
          "url": "https://actawp.natacio.cat/es/tournament/1317471/match/144027300/results"
        },
        {
          "team1": "U.E. D'HORTA",
          "team2": "C.N. PREMIÀ",
          "team1_logo": "https://cdn.leverade.com/thumbnails/AaEBEa7OVvwB.30x30.jpg",
          "team2_logo": "https://cdn.leverade.com/thumbnails/AatzEPbjSvDt.30x30.jpg",
          "score": "22-8",
          "date": "",
          "jornada": 4,
          "url": "https://actawp.natacio.cat/es/tournament/1317471/match/143574177/results"
        },
        {
          "team1": "U.E. D'HORTA",
          "team2": "C.N. ATL BARCELONETA",
          "team1_logo": "https://cdn.leverade.com/thumbnails/AaEBEa7OVvwB.30x30.jpg",
          "team2_logo": "https://cdn.leverade.com/thumbnails/AaS9iMCevN9M.30x30.jpg",
          "score": "5-22",
          "date": "",
          "jornada": 5,
          "url": "https://actawp.natacio.cat/es/tournament/1317471/match/143574180/results"
        }
      ],
      "form": [
        "W",
        "L",
        "W",
        "W",
        "L"
      ],
      "form_string": "WLWWL",
      "top_scorers": [
        {
          "name": "JEFFERSON FERRERAS SALDAÑA",
          "goals": 30,
          "games": 10,
          "exclusions": 10,
          "penalty_goals": 2,
          "avg_goals": 3.0
        },
        {
          "name": "MARC SUAREZ VAN DAM",
          "goals": 30,
          "games": 11,
          "exclusions": 6,
          "penalty_goals": 0,
          "avg_goals": 2.73
        },
        {
          "name": "POL FONT SUAREZ",
          "goals": 30,
          "games": 10,
          "exclusions": 4,
          "penalty_goals": 9,
          "avg_goals": 3.0
        },
        {
          "name": "ORIOL HURTADO CLOPES",
          "goals": 24,
          "games": 6,
          "exclusions": 8,
          "penalty_goals": 9,
          "avg_goals": 4.0
        },
        {
          "name": "BERNAL PARIENTE LOPEZ",
          "goals": 11,
          "games": 11,
          "exclusions": 5,
          "penalty_goals": 1,
          "avg_goals": 1.0
        }
      ],
      "stats": {
        "total_gf": 64,
        "total_gc": 68,
        "avg_gf": 12.8,
        "avg_gc": 13.6,
        "matches_played": 5,
        "wins": 3,
        "draws": 0,
        "losses": 2,
        "trend": "hot",
        "total_exclusions": 33
      }
    },
    "C.N. BARCELONA": {
      "team_id": "15612054",
      "last_results": [
        {
          "team1": "C.N. BARCELONA",
          "team2": "C.N. MONTJUIC A",
          "team1_logo": "https://cdn.leverade.com/thumbnails/AaT38Tf1E4Fg.30x30.jpg",
          "team2_logo": "https://cdn.leverade.com/thumbnails/AaLZ2cLfo4fC.30x30.jpg",
          "score": "23-3",
          "date": "",
          "jornada": 1,
          "url": "https://actawp.natacio.cat/es/tournament/1317471/match/144027301/results"
        },
        {
          "team1": "C.N. BARCELONA",
          "team2": "C.N. CATALUNYA",
          "team1_logo": "https://cdn.leverade.com/thumbnails/AaT38Tf1E4Fg.30x30.jpg",
          "team2_logo": "https://cdn.leverade.com/thumbnails/AajxOQYj1UBb.30x30.jpg",
          "score": "21-7",
          "date": "",
          "jornada": 2,
          "url": "https://actawp.natacio.cat/es/tournament/1317471/match/143574209/results"
        },
        {
          "team1": "C.N. MATARÓ",
          "team2": "C.N. BARCELONA",
          "team1_logo": "https://cdn.leverade.com/thumbnails/AaOLLadIjC6E.30x30.jpg",
          "team2_logo": "https://cdn.leverade.com/thumbnails/AaT38Tf1E4Fg.30x30.jpg",
          "score": "9-13",
          "date": "",
          "jornada": 3,
          "url": "https://actawp.natacio.cat/es/tournament/1317471/match/143574207/results"
        },
        {
          "team1": "C.N. SANT ANDREU",
          "team2": "C.N. BARCELONA",
          "team1_logo": "https://cdn.leverade.com/thumbnails/AaTcV9fsgKzp.30x30.jpg",
          "team2_logo": "https://cdn.leverade.com/thumbnails/AaT38Tf1E4Fg.30x30.jpg",
          "score": "7-16",
          "date": "",
          "jornada": 4,
          "url": "https://actawp.natacio.cat/es/tournament/1317471/match/143574206/results"
        },
        {
          "team1": "C.N. CATALUNYA",
          "team2": "C.N. BARCELONA",
          "team1_logo": "https://cdn.leverade.com/thumbnails/AajxOQYj1UBb.30x30.jpg",
          "team2_logo": "https://cdn.leverade.com/thumbnails/AaT38Tf1E4Fg.30x30.jpg",
          "score": "7-28",
          "date": "",
          "jornada": 5,
          "url": "https://actawp.natacio.cat/es/tournament/1317471/match/143574203/results"
        }
      ],
      "form": [
        "W",
        "W",
        "W",
        "W",
        "W"
      ],
      "form_string": "WWWWW",
      "top_scorers": [
        {
          "name": "SVILEN PIRALKOV COELLO",
          "goals": 27,
          "games": 9,
          "exclusions": 5,
          "penalty_goals": 5,
          "avg_goals": 3.0
        },
        {
          "name": "MARIO PAZ NUÑEZ",
          "goals": 26,
          "games": 9,
          "exclusions": 9,
          "penalty_goals": 1,
          "avg_goals": 2.89
        },
        {
          "name": "ERIC PEDREROL SARDAÑA",
          "goals": 16,
          "games": 9,
          "exclusions": 6,
          "penalty_goals": 5,
          "avg_goals": 1.78
        },
        {
          "name": "PAU ORTIZ MINGUET",
          "goals": 15,
          "games": 8,
          "exclusions": 8,
          "penalty_goals": 0,
          "avg_goals": 1.88
        },
        {
          "name": "IGNACIO MERCEDES ECHEVERRIA",
          "goals": 12,
          "games": 7,
          "exclusions": 1,
          "penalty_goals": 1,
          "avg_goals": 1.71
        }
      ],
      "stats": {
        "total_gf": 101,
        "total_gc": 33,
        "avg_gf": 20.2,
        "avg_gc": 6.6,
        "matches_played": 5,
        "wins": 5,
        "draws": 0,
        "losses": 0,
        "trend": "hot",
        "total_exclusions": 29
      }
    },
    "C.N. SANT ANDREU": {
      "team_id": "15617612",
      "last_results": [
        {
          "team1": "C.N. SANT ANDREU",
          "team2": "C.N. SABADELL",
          "team1_logo": "https://cdn.leverade.com/thumbnails/AaTcV9fsgKzp.30x30.jpg",
          "team2_logo": "https://cdn.leverade.com/thumbnails/AaJFwTq1SdZo.30x30.jpg",
          "score": "8-14",
          "date": "",
          "jornada": 1,
          "url": "https://actawp.natacio.cat/es/tournament/1317471/match/144027302/results"
        },
        {
          "team1": "C.N. MONTJUIC A",
          "team2": "C.N. SANT ANDREU",
          "team1_logo": "https://cdn.leverade.com/thumbnails/AaLZ2cLfo4fC.30x30.jpg",
          "team2_logo": "https://cdn.leverade.com/thumbnails/AaTcV9fsgKzp.30x30.jpg",
          "score": "12-15",
          "date": "",
          "jornada": 2,
          "url": "https://actawp.natacio.cat/es/tournament/1317471/match/144027306/results"
        },
        {
          "team1": "C.N. SANT ANDREU",
          "team2": "C.N. MATARÓ",
          "team1_logo": "https://cdn.leverade.com/thumbnails/AaTcV9fsgKzp.30x30.jpg",
          "team2_logo": "https://cdn.leverade.com/thumbnails/AaOLLadIjC6E.30x30.jpg",
          "score": "17-16",
          "date": "",
          "jornada": 3,
          "url": "https://actawp.natacio.cat/es/tournament/1317471/match/143574210/results"
        },
        {
          "team1": "C.N. CATALUNYA",
          "team2": "C.N. SANT ANDREU",
          "team1_logo": "https://cdn.leverade.com/thumbnails/AajxOQYj1UBb.30x30.jpg",
          "team2_logo": "https://cdn.leverade.com/thumbnails/AaTcV9fsgKzp.30x30.jpg",
          "score": "17-15",
          "date": "",
          "jornada": 4,
          "url": "https://actawp.natacio.cat/es/tournament/1317471/match/143574208/results"
        },
        {
          "team1": "C.N. SANT ANDREU",
          "team2": "C.N. BARCELONA",
          "team1_logo": "https://cdn.leverade.com/thumbnails/AaTcV9fsgKzp.30x30.jpg",
          "team2_logo": "https://cdn.leverade.com/thumbnails/AaT38Tf1E4Fg.30x30.jpg",
          "score": "7-16",
          "date": "",
          "jornada": 5,
          "url": "https://actawp.natacio.cat/es/tournament/1317471/match/143574206/results"
        }
      ],
      "form": [
        "L",
        "W",
        "W",
        "L",
        "L"
      ],
      "form_string": "LWWLL",
      "top_scorers": [
        {
          "name": "EYAL VASHDI",
          "goals": 27,
          "games": 9,
          "exclusions": 11,
          "penalty_goals": 12,
          "avg_goals": 3.0
        },
        {
          "name": "ALEJANDRO RUDZEVICH RAMIREZ",
          "goals": 23,
          "games": 9,
          "exclusions": 8,
          "penalty_goals": 7,
          "avg_goals": 2.56
        },
        {
          "name": "AXEL GUICH JIMENEZ",
          "goals": 17,
          "games": 9,
          "exclusions": 5,
          "penalty_goals": 2,
          "avg_goals": 1.89
        },
        {
          "name": "MARTI PIÑEIRA GONZALEZ",
          "goals": 16,
          "games": 9,
          "exclusions": 5,
          "penalty_goals": 4,
          "avg_goals": 1.78
        },
        {
          "name": "JOSE CESTERO ALCAIN",
          "goals": 12,
          "games": 8,
          "exclusions": 8,
          "penalty_goals": 1,
          "avg_goals": 1.5
        }
      ],
      "stats": {
        "total_gf": 62,
        "total_gc": 75,
        "avg_gf": 12.4,
        "avg_gc": 15.0,
        "matches_played": 5,
        "wins": 2,
        "draws": 0,
        "losses": 3,
        "trend": "hot",
        "total_exclusions": 37
      }
    },
    "C.E. MEDITERRANI": {
      "team_id": "15609737",
      "last_results": [
        {
          "team1": "U.E. D'HORTA",
          "team2": "C.E. MEDITERRANI",
          "team1_logo": "https://cdn.leverade.com/thumbnails/AaEBEa7OVvwB.30x30.jpg",
          "team2_logo": "https://cdn.leverade.com/thumbnails/AasntmnZMsxi.30x30.jpg",
          "score": "10-8",
          "date": "",
          "jornada": 1,
          "url": "https://actawp.natacio.cat/es/tournament/1317471/match/144027311/results"
        },
        {
          "team1": "C.E. MEDITERRANI",
          "team2": "C.N. SABADELL",
          "team1_logo": "https://cdn.leverade.com/thumbnails/AasntmnZMsxi.30x30.jpg",
          "team2_logo": "https://cdn.leverade.com/thumbnails/AaJFwTq1SdZo.30x30.jpg",
          "score": "13-14",
          "date": "",
          "jornada": 2,
          "url": "https://actawp.natacio.cat/es/tournament/1317471/match/144027307/results"
        },
        {
          "team1": "C.N. ATL BARCELONETA",
          "team2": "C.E. MEDITERRANI",
          "team1_logo": "https://cdn.leverade.com/thumbnails/AaS9iMCevN9M.30x30.jpg",
          "team2_logo": "https://cdn.leverade.com/thumbnails/AasntmnZMsxi.30x30.jpg",
          "score": "11-5",
          "date": "",
          "jornada": 3,
          "url": "https://actawp.natacio.cat/es/tournament/1317471/match/144027303/results"
        },
        {
          "team1": "C.N. MONTJUIC B",
          "team2": "C.E. MEDITERRANI",
          "team1_logo": "https://cdn.leverade.com/thumbnails/AaLZ2cLfo4fC.30x30.jpg",
          "team2_logo": "https://cdn.leverade.com/thumbnails/AasntmnZMsxi.30x30.jpg",
          "score": "6-19",
          "date": "",
          "jornada": 4,
          "url": "https://actawp.natacio.cat/es/tournament/1317471/match/143574248/results"
        },
        {
          "team1": "C.E. MEDITERRANI",
          "team2": "C.N. TERRASSA",
          "team1_logo": "https://cdn.leverade.com/thumbnails/AasntmnZMsxi.30x30.jpg",
          "team2_logo": "https://cdn.leverade.com/thumbnails/rfen_f74fa6fe.30x30.jpg",
          "score": "11-12",
          "date": "",
          "jornada": 5,
          "url": "https://actawp.natacio.cat/es/tournament/1317471/match/143574245/results"
        }
      ],
      "form": [
        "L",
        "L",
        "L",
        "W",
        "L"
      ],
      "form_string": "LLLWL",
      "top_scorers": [
        {
          "name": "ALEIX GUERRERO GARCIA",
          "goals": 38,
          "games": 11,
          "exclusions": 9,
          "penalty_goals": 10,
          "avg_goals": 3.45
        },
        {
          "name": "BERNAT MARTINEZ VAZQUEZ",
          "goals": 25,
          "games": 11,
          "exclusions": 6,
          "penalty_goals": 1,
          "avg_goals": 2.27
        },
        {
          "name": "ORIOL LOPEZ CHARLES",
          "goals": 14,
          "games": 11,
          "exclusions": 7,
          "penalty_goals": 0,
          "avg_goals": 1.27
        },
        {
          "name": "MARC MCCAVANAGH PEREZ",
          "goals": 12,
          "games": 11,
          "exclusions": 4,
          "penalty_goals": 0,
          "avg_goals": 1.09
        },
        {
          "name": "MATIAS MIRANDA FERREIRA",
          "goals": 11,
          "games": 10,
          "exclusions": 11,
          "penalty_goals": 1,
          "avg_goals": 1.1
        }
      ],
      "stats": {
        "total_gf": 56,
        "total_gc": 53,
        "avg_gf": 11.2,
        "avg_gc": 10.6,
        "matches_played": 5,
        "wins": 1,
        "draws": 0,
        "losses": 4,
        "trend": "cold",
        "total_exclusions": 37
      }
    },
    "C.N. MONTJUIC A": {
      "team_id": "15617365",
      "last_results": [
        {
          "team1": "C.N. SABADELL",
          "team2": "C.N. MONTJUIC A",
          "team1_logo": "https://cdn.leverade.com/thumbnails/AaJFwTq1SdZo.30x30.jpg",
          "team2_logo": "https://cdn.leverade.com/thumbnails/AaLZ2cLfo4fC.30x30.jpg",
          "score": "23-6",
          "date": "",
          "jornada": 1,
          "url": "https://actawp.natacio.cat/es/tournament/1317471/match/144027310/results"
        },
        {
          "team1": "C.N. MONTJUIC A",
          "team2": "C.N. SANT ANDREU",
          "team1_logo": "https://cdn.leverade.com/thumbnails/AaLZ2cLfo4fC.30x30.jpg",
          "team2_logo": "https://cdn.leverade.com/thumbnails/AaTcV9fsgKzp.30x30.jpg",
          "score": "12-15",
          "date": "",
          "jornada": 2,
          "url": "https://actawp.natacio.cat/es/tournament/1317471/match/144027306/results"
        },
        {
          "team1": "C.N. BARCELONA",
          "team2": "C.N. MONTJUIC A",
          "team1_logo": "https://cdn.leverade.com/thumbnails/AaT38Tf1E4Fg.30x30.jpg",
          "team2_logo": "https://cdn.leverade.com/thumbnails/AaLZ2cLfo4fC.30x30.jpg",
          "score": "23-3",
          "date": "",
          "jornada": 3,
          "url": "https://actawp.natacio.cat/es/tournament/1317471/match/144027301/results"
        },
        {
          "team1": "C.N. POBLE NOU",
          "team2": "C.N. MONTJUIC A",
          "team1_logo": "https://cdn.leverade.com/thumbnails/AavYwrQJ36uU.30x30.jpg",
          "team2_logo": "https://cdn.leverade.com/thumbnails/AaLZ2cLfo4fC.30x30.jpg",
          "score": "12-19",
          "date": "",
          "jornada": 4,
          "url": "https://actawp.natacio.cat/es/tournament/1317471/match/143574236/results"
        },
        {
          "team1": "C.N. SANT FELIU",
          "team2": "C.N. MONTJUIC A",
          "team1_logo": "https://cdn.leverade.com/thumbnails/AaHuNvh2GCD0.30x30.jpg",
          "team2_logo": "https://cdn.leverade.com/thumbnails/AaLZ2cLfo4fC.30x30.jpg",
          "score": "11-14",
          "date": "",
          "jornada": 5,
          "url": "https://actawp.natacio.cat/es/tournament/1317471/match/143574231/results"
        }
      ],
      "form": [
        "L",
        "L",
        "L",
        "W",
        "W"
      ],
      "form_string": "LLLWW",
      "top_scorers": [
        {
          "name": "PAU RUEDA CAMINS",
          "goals": 24,
          "games": 8,
          "exclusions": 6,
          "penalty_goals": 6,
          "avg_goals": 3.0
        },
        {
          "name": "GABRIEL GARCIA SORIA",
          "goals": 23,
          "games": 10,
          "exclusions": 10,
          "penalty_goals": 0,
          "avg_goals": 2.3
        },
        {
          "name": "MARC PARERA ALONSO",
          "goals": 17,
          "games": 9,
          "exclusions": 10,
          "penalty_goals": 6,
          "avg_goals": 1.89
        },
        {
          "name": "MARIO PERIBAÑEZ GISBERT",
          "goals": 14,
          "games": 8,
          "exclusions": 9,
          "penalty_goals": 3,
          "avg_goals": 1.75
        },
        {
          "name": "LUCA JOVANOVSKI GALLEGO",
          "goals": 13,
          "games": 9,
          "exclusions": 8,
          "penalty_goals": 2,
          "avg_goals": 1.44
        }
      ],
      "stats": {
        "total_gf": 54,
        "total_gc": 84,
        "avg_gf": 10.8,
        "avg_gc": 16.8,
        "matches_played": 5,
        "wins": 2,
        "draws": 0,
        "losses": 3,
        "trend": "cold",
        "total_exclusions": 43
      }
    }
  },
  "last_update": "2026-02-04T18:25:59.708282+01:00",
  "workflow_run": "2304"
}